mpiexec/mpiexec
mpiexec/__init__.py
mpiexec/__main__.py
mpiexec/hydra_pmi_proxy
mpi4py/run.pyi
mpi4py/py.typed
mpi4py/bench.py
mpi4py/MPI.pxd
mpi4py/libmpi.pxd
mpi4py/__init__.py
mpi4py/__init__.pxd
mpi4py/__main__.py
mpi4py/MPI.pyi
mpi4py/mpi.cfg
mpi4py/dl.pyi
mpi4py/run.py
mpi4py/dl.cpython-310-x86_64-linux-gnu.so
mpi4py/MPI.cpython-310-x86_64-linux-gnu.so
mpi4py/__main__.pyi
mpi4py/__init__.pyi
mpi4py/bench.pyi
mpi4py/include/mpi4py/mpi4py.MPI.h
mpi4py/include/mpi4py/mpi4py.MPI_api.h
mpi4py/include/mpi4py/mpi.pxi
mpi4py/include/mpi4py/mpi4py.i
mpi4py/include/mpi4py/mpi4py.h
mpi4py/futures/pool.py
mpi4py/futures/_core.py
mpi4py/futures/_lib.pyi
mpi4py/futures/__init__.py
mpi4py/futures/server.pyi
mpi4py/futures/pool.pyi
mpi4py/futures/aplus.pyi
mpi4py/futures/__main__.py
mpi4py/futures/aplus.py
mpi4py/futures/_lib.py
mpi4py/futures/_core.pyi
mpi4py/futures/server.py
mpi4py/futures/_base.py
mpi4py/futures/__main__.pyi
mpi4py/futures/__init__.pyi
mpi4py/util/pkl5.pyi
mpi4py/util/__init__.py
mpi4py/util/dtlib.py
mpi4py/util/dtlib.pyi
mpi4py/util/pkl5.py
mpi4py/util/__init__.pyi
mpi4py/lib-pmpi/libvt.so
mpi4py/lib-pmpi/libvt-mpi.so
mpi4py/lib-pmpi/libvt-hyb.so
mpi4py/lib-pmpi/libmpe.so
mpi4py_mpich.libs/libmpi-1e85b3e0.so.12.1.8
mpi4py_mpich-3.1.2.dist-info/entry_points.txt
mpi4py_mpich-3.1.2.dist-info/top_level.txt
mpi4py_mpich-3.1.2.dist-info/LICENSE.rst
mpi4py_mpich-3.1.2.dist-info/WHEEL
mpi4py_mpich-3.1.2.dist-info/RECORD
mpi4py_mpich-3.1.2.dist-info/METADATA
