Metadata-Version: 2.1
Name: mpi4py-mpich
Version: 3.1.2
Summary: Python bindings for MPI (includes MPICH binaries)
Home-page: https://github.com/mpi4py/mpi4py/
Author: Lisandro Dalcin
Author-email: dalcinl@gmail.com
Maintainer: Lisandro Dalcin
Maintainer-email: dalcinl@gmail.com
License: BSD
Download-URL: https://github.com/mpi4py/mpi4py/releases/download/3.1.2/mpi4py-3.1.2.tar.gz
Keywords: scientific computing,parallel computing,message passing interface,MPI
Platform: POSIX
Platform: Linux
Platform: macOS
Platform: FreeBSD
Platform: Windows
Classifier: Development Status :: 5 - Production/Stable
Classifier: Intended Audience :: Developers
Classifier: Intended Audience :: Science/Research
Classifier: License :: OSI Approved :: BSD License
Classifier: Operating System :: MacOS
Classifier: Operating System :: MacOS :: MacOS X
Classifier: Operating System :: Microsoft :: Windows
Classifier: Operating System :: POSIX
Classifier: Operating System :: POSIX :: BSD
Classifier: Operating System :: POSIX :: Linux
Classifier: Operating System :: Unix
Classifier: Programming Language :: C
Classifier: Programming Language :: Cython
Classifier: Programming Language :: Python
Classifier: Programming Language :: Python :: 2
Classifier: Programming Language :: Python :: 2.7
Classifier: Programming Language :: Python :: 3
Classifier: Programming Language :: Python :: 3.5
Classifier: Programming Language :: Python :: 3.6
Classifier: Programming Language :: Python :: 3.7
Classifier: Programming Language :: Python :: 3.8
Classifier: Programming Language :: Python :: 3.9
Classifier: Programming Language :: Python :: 3.10
Classifier: Programming Language :: Python :: Implementation :: CPython
Classifier: Programming Language :: Python :: Implementation :: PyPy
Classifier: Topic :: Scientific/Engineering
Classifier: Topic :: Software Development :: Libraries :: Python Modules
Classifier: Topic :: System :: Distributed Computing
Provides: mpi4py
Requires-Python: >=2.7, !=3.0.*, !=3.1.*, !=3.2.*, !=3.3.*, !=3.4.*
License-File: LICENSE.rst
